ytu/__init__.py
ytu/ytu.py
ytu-0.2.0.dist-info/AUTHORS.rst
ytu-0.2.0.dist-info/LICENSE
ytu-0.2.0.dist-info/METADATA
ytu-0.2.0.dist-info/WHEEL
ytu-0.2.0.dist-info/top_level.txt
ytu-0.2.0.dist-info/RECORD
