Metadata-Version: 2.1
Name: ytu
Version: 0.2.0
Summary: A library to extract information from YouTube URLs.
Home-page: https://github.com/yaph/ytu
Author: Ramiro Gómez
Author-email: code@ramiro.org
License: MIT license
Keywords: youtube,url,uri,video id
Platform: UNKNOWN
Classifier: Development Status :: 5 - Production/Stable
Classifier: Intended Audience :: Developers
Classifier: License :: OSI Approved :: MIT License
Classifier: Natural Language :: English
Classifier: Programming Language :: Python :: 3
Classifier: Programming Language :: Python :: 3.5
Classifier: Programming Language :: Python :: 3.6
Classifier: Programming Language :: Python :: 3.7
